journeyplanner/__init__.py
journeyplanner/__main__.py
journeyplanner/config.py
journeyplanner/error.py
journeyplanner/request.py
journeyplanner/type.py
journeyplanner-1.0.1.dist-info/LICENSE
journeyplanner-1.0.1.dist-info/METADATA
journeyplanner-1.0.1.dist-info/WHEEL
journeyplanner-1.0.1.dist-info/top_level.txt
journeyplanner-1.0.1.dist-info/RECORD
