Metadata-Version: 2.1
Name: journeyplanner
Version: 1.0.1
Summary: Journey Planner API client library
Home-page: https://github.com/bytesandbrains/journeyplanner-python
Author: Bytes & Brains
Author-email: developers@bytesandbrains.com
License: MIT
Platform: UNKNOWN
